django_auth_manager/__init__.py
django_auth_manager/constants.py
django_auth_manager/management/__init__.py
django_auth_manager/management/commands/__init__.py
django_auth_manager/management/commands/fetch_groups.py
django_auth_manager/management/commands/fetch_users.py
django_auth_manager-0.1.0.dist-info/LICENSE
django_auth_manager-0.1.0.dist-info/METADATA
django_auth_manager-0.1.0.dist-info/WHEEL
django_auth_manager-0.1.0.dist-info/RECORD
